rorocloud/__init__.py
rorocloud/auth.py
rorocloud/cli.py
rorocloud/client.py
rorocloud/utils.py
rorocloud/version.py
rorocloud-0.2.3.dist-info/DESCRIPTION.rst
rorocloud-0.2.3.dist-info/METADATA
rorocloud-0.2.3.dist-info/RECORD
rorocloud-0.2.3.dist-info/WHEEL
rorocloud-0.2.3.dist-info/entry_points.txt
rorocloud-0.2.3.dist-info/metadata.json
rorocloud-0.2.3.dist-info/top_level.txt
tests/__init__.py
tests/test_auth.py
tests/test_cli.py
tests2/__init__.py
