Metadata-Version: 2.0
Name: rorocloud
Version: 0.2.3
Summary: UNKNOWN
Home-page: UNKNOWN
Author: rorodata
Author-email: rorodata.team@gmail.com
License: UNKNOWN
Platform: UNKNOWN
Requires-Dist: click (==6.7)
Requires-Dist: requests (==2.13.0)
Requires-Dist: tabulate (==0.7.7)
Requires-Dist: web.py (>=0.40.dev)
